{
  "name": "Weather",
  "sourceLang": {
    "langId": "en",
    "partsOfSpeech": [
      "noun",
      "verb",
      "adjective",
      "adverb",
      "pronoun",
      "preposition",
      "conjunction",
      "interjection",
      "article"
    ]
  },
  "targetLang": {
    "langId": "hi",
    "partsOfSpeech": [
      "संज्ञा",
      "क्रिया",
      "विशेषण",
      "क्रियाविशेषण",
      "सर्वनाम",
      "पूर्वसर्ग",
      "संयोजक",
      "विस्मयादिबोधक",
      "लेख"
    ]
  },
  "cards": [
    {
      "words": [
        {
          "word": "atmospheric",
          "transcription": "ˌætməs'ferik",
          "partOfSpeech": "adjective",
          "translations": [
            [
              "वायुमंडलीय"
            ]
          ]
        }
      ],
      "answered": 0
    },
    {
      "words": [
        {
          "word": "weather",
          "transcription": "'weðə",
          "partOfSpeech": "noun",
          "translations": [
            [
              "मौसम"
            ]
          ]
        }
      ],
      "answered": 0
    },
    {
      "words": [
        {
          "word": "snow",
          "transcription": "snəu",
          "partOfSpeech": "noun",
          "translations": [
            [
              "बर्फ"
            ]
          ]
        }
      ],
      "answered": 0
    },
    {
      "words": [
        {
          "word": "rain",
          "transcription": "rein",
          "partOfSpeech": "noun",
          "translations": [
            [
              "बारिश"
            ]
          ]
        }
      ],
      "answered": 0
    },
    {
      "words": [
        {
          "word": "wind",
          "transcription": "wind",
          "partOfSpeech": "noun",
          "translations": [
            [
              "हवा"
            ]
          ]
        }
      ],
      "answered": 0
    },
    {
      "words": [
        {
          "word": "hail",
          "transcription": "heil",
          "partOfSpeech": "noun",
          "translations": [
            [
              "ओले"
            ]
          ]
        }
      ],
      "answered": 0
    },
    {
      "words": [
        {
          "word": "thunderstorm",
          "transcription": "'θʌndəstɔːm",
          "partOfSpeech": "noun",
          "translations": [
            [
              "आंधी-तूफान"
            ]
          ]
        }
      ],
      "answered": 0
    },
    {
      "words": [
        {
          "word": "precipitation",
          "transcription": "priˌsipi'teiʃ(ə)n",
          "partOfSpeech": "noun",
          "translations": [
            [
              "वर्षा"
            ]
          ]
        }
      ],
      "answered": 0
    },
    {
      "words": [
        {
          "word": "thunder",
          "transcription": "'θʌndə",
          "partOfSpeech": "noun",
          "translations": [
            [
              "गरज"
            ]
          ]
        }
      ],
      "answered": 0
    },
    {
      "words": [
        {
          "word": "lightning",
          "transcription": "'laitniŋ",
          "partOfSpeech": "noun",
          "translations": [
            [
              "बिजली"
            ]
          ]
        }
      ],
      "answered": 0
    },
    {
      "words": [
        {
          "word": "anticyclone",
          "transcription": "'ænti'saikləun",
          "partOfSpeech": "noun",
          "translations": [
            [
              "प्रतिचक्रवात"
            ]
          ]
        }
      ],
      "answered": 0
    },
    {
      "words": [
        {
          "word": "atmosphere",
          "transcription": "'ætməsfiə",
          "partOfSpeech": "noun",
          "translations": [
            [
              "वायुमंडल"
            ]
          ]
        }
      ],
      "answered": 0
    },
    {
      "words": [
        {
          "word": "barometer",
          "transcription": "bə'rɔmitə",
          "partOfSpeech": "noun",
          "translations": [
            [
              "बैरोमीटर"
            ]
          ]
        }
      ],
      "answered": 0
    },
    {
      "words": [
        {
          "word": "windy",
          "transcription": "'windi",
          "partOfSpeech": "adjective",
          "translations": [
            [
              "तेज हवा वाला"
            ]
          ]
        }
      ],
      "answered": 0
    },
    {
      "words": [
        {
          "word": "humidity",
          "transcription": "hjuː'midəti",
          "partOfSpeech": "noun",
          "translations": [
            [
              "नमी"
            ]
          ]
        }
      ],
      "answered": 0
    },
    {
      "words": [
        {
          "word": "humid",
          "transcription": "'hjuːmid",
          "partOfSpeech": "adjective",
          "translations": [
            [
              "नम"
            ]
          ]
        }
      ],
      "answered": 0
    },
    {
      "words": [
        {
          "word": "moist",
          "transcription": "mɔist",
          "partOfSpeech": "adjective",
          "translations": [
            [
              "गीला"
            ]
          ]
        }
      ],
      "answered": 0
    },
    {
      "words": [
        {
          "word": "damp",
          "transcription": "dæmp",
          "partOfSpeech": "adjective",
          "translations": [
            [
              "सीलन"
            ]
          ]
        }
      ],
      "answered": 0
    },
    {
      "words": [
        {
          "word": "sunrise",
          "transcription": "'sʌnraiz",
          "partOfSpeech": "noun",
          "translations": [
            [
              "सूर्योदय"
            ]
          ]
        }
      ],
      "answered": 0
    },
    {
      "words": [
        {
          "word": "degree",
          "transcription": "di'griː",
          "partOfSpeech": "noun",
          "translations": [
            [
              "डिग्री"
            ]
          ]
        }
      ],
      "answered": 0
    },
    {
      "words": [
        {
          "word": "pressure",
          "transcription": "'preʃə",
          "partOfSpeech": "noun",
          "translations": [
            [
              "दबाव"
            ]
          ]
        }
      ],
      "answered": 0
    },
    {
      "words": [
        {
          "word": "stuffy",
          "transcription": "'stʌfi",
          "partOfSpeech": "adjective",
          "translations": [
            [
              "घुटनभरा"
            ]
          ]
        }
      ],
      "answered": 0
    },
    {
      "words": [
        {
          "word": "heat",
          "transcription": "hiːt",
          "partOfSpeech": "noun",
          "translations": [
            [
              "गर्मी"
            ]
          ]
        }
      ],
      "answered": 0
    },
    {
      "words": [
        {
          "word": "hot",
          "transcription": "hɔt",
          "partOfSpeech": "adjective",
          "translations": [
            [
              "गरम"
            ]
          ]
        }
      ],
      "answered": 0
    },
    {
      "words": [
        {
          "word": "sunset",
          "transcription": "'sʌnset",
          "partOfSpeech": "noun",
          "translations": [
            [
              "सूर्यास्त"
            ]
          ]
        }
      ],
      "answered": 0
    },
    {
      "words": [
        {
          "word": "frost",
          "transcription": "frɔst",
          "partOfSpeech": "noun",
          "translations": [
            [
              "पाला"
            ]
          ]
        }
      ],
      "answered": 0
    },
    {
      "words": [
        {
          "word": "drizzle",
          "transcription": "'drizl",
          "partOfSpeech": "noun",
          "translations": [
            [
              "बूंदाबांदी"
            ]
          ]
        }
      ],
      "answered": 0
    },
    {
      "words": [
        {
          "word": "haze",
          "transcription": "heiz",
          "partOfSpeech": "noun",
          "translations": [
            [
              "कोहरा"
            ]
          ]
        }
      ],
      "answered": 0
    },
    {
      "words": [
        {
          "word": "ice",
          "transcription": "ais",
          "partOfSpeech": "noun",
          "translations": [
            [
              "बर्फ"
            ]
          ]
        }
      ],
      "answered": 0
    },
    {
      "words": [
        {
          "word": "shower",
          "transcription": "'ʃəuə",
          "partOfSpeech": "noun",
          "translations": [
            [
              "बौछार"
            ]
          ]
        }
      ],
      "answered": 0
    },
    {
      "words": [
        {
          "word": "puddle",
          "transcription": "'pʌdl",
          "partOfSpeech": "noun",
          "translations": [
            [
              "गड्ढे में पानी"
            ]
          ]
        }
      ],
      "answered": 0
    },
    {
      "words": [
        {
          "word": "meteorology",
          "transcription": "ˌmiːti(ə)'rɔləʤi",
          "partOfSpeech": "noun",
          "translations": [
            [
              "मौसम विज्ञान"
            ]
          ]
        }
      ],
      "answered": 0
    },
    {
      "words": [
        {
          "word": "cloudy",
          "transcription": "'klaudi",
          "partOfSpeech": "adjective",
          "translations": [
            [
              "बादलों से भरा"
            ]
          ]
        }
      ],
      "answered": 0
    },
    {
      "words": [
        {
          "word": "thaw",
          "transcription": "θɔː",
          "partOfSpeech": "noun",
          "translations": [
            [
              "पिघलना"
            ]
          ]
        }
      ],
      "answered": 0
    },
    {
      "words": [
        {
          "word": "cool",
          "transcription": "kuːl",
          "partOfSpeech": "adjective",
          "translations": [
            [
              "ठंडा"
            ]
          ]
        }
      ],
      "answered": 0
    },
    {
      "words": [
        {
          "word": "dusty",
          "transcription": "'dʌsti",
          "partOfSpeech": "adjective",
          "translations": [
            [
              "धूलभरा"
            ]
          ]
        }
      ],
      "answered": 0
    },
    {
      "words": [
        {
          "word": "rainbow",
          "transcription": "'reinbəu",
          "partOfSpeech": "noun",
          "translations": [
            [
              "इंद्रधनुष"
            ]
          ]
        }
      ],
      "answered": 0
    },
    {
      "words": [
        {
          "word": "fresh",
          "transcription": "freʃ",
          "partOfSpeech": "adjective",
          "translations": [
            [
              "ताज़ा"
            ]
          ]
        }
      ],
      "answered": 0
    },
    {
      "words": [
        {
          "word": "slippery",
          "transcription": "'slipəri",
          "partOfSpeech": "adjective",
          "translations": [
            [
              "फिसलन भरा"
            ]
          ]
        }
      ],
      "answered": 0
    },
    {
      "words": [
        {
          "word": "slush",
          "transcription": "slʌʃ",
          "partOfSpeech": "noun",
          "translations": [
            [
              "कीचड़"
            ]
          ]
        }
      ],
      "answered": 0
    },
    {
      "words": [
        {
          "word": "smog",
          "transcription": "smɔg",
          "partOfSpeech": "noun",
          "translations": [
            [
              "धुंध"
            ]
          ]
        }
      ],
      "answered": 0
    },
    {
      "words": [
        {
          "word": "snowfall",
          "transcription": "",
          "partOfSpeech": "noun",
          "translations": [
            [
              "बर्फबारी"
            ]
          ]
        }
      ],
      "answered": 0
    },
    {
      "words": [
        {
          "word": "sunny",
          "transcription": "'sʌni",
          "partOfSpeech": "adjective",
          "translations": [
            [
              "धूपदार"
            ]
          ]
        }
      ],
      "answered": 0
    },
    {
      "words": [
        {
          "word": "dry",
          "transcription": "drai",
          "partOfSpeech": "adjective",
          "translations": [
            [
              "सूखा"
            ]
          ]
        }
      ],
      "answered": 0
    },
    {
      "words": [
        {
          "word": "wet",
          "transcription": "wet",
          "partOfSpeech": "adjective",
          "translations": [
            [
              "गीला"
            ]
          ]
        }
      ],
      "answered": 0
    },
    {
      "words": [
        {
          "word": "temperature",
          "transcription": "'tempriʧə",
          "partOfSpeech": "noun",
          "translations": [
            [
              "तापमान"
            ]
          ]
        }
      ],
      "answered": 0
    },
    {
      "words": [
        {
          "word": "warm",
          "transcription": "wɔːm",
          "partOfSpeech": "adjective",
          "translations": [
            [
              "गुनगुना"
            ]
          ]
        }
      ],
      "answered": 0
    },
    {
      "words": [
        {
          "word": "thermometer",
          "transcription": "θə'mɔmitə",
          "partOfSpeech": "noun",
          "translations": [
            [
              "थर्मामीटर"
            ]
          ]
        }
      ],
      "answered": 0
    },
    {
      "words": [
        {
          "word": "fog",
          "transcription": "fɔg",
          "partOfSpeech": "noun",
          "translations": [
            [
              "कोहरा"
            ]
          ]
        }
      ],
      "answered": 0
    },
    {
      "words": [
        {
          "word": "mist",
          "transcription": "mist",
          "partOfSpeech": "noun",
          "translations": [
            [
              "धुंध"
            ]
          ]
        }
      ],
      "answered": 0
    },
    {
      "words": [
        {
          "word": "foggy",
          "transcription": "'fɔgi",
          "partOfSpeech": "adjective",
          "translations": [
            [
              "कोहरे से भरा"
            ]
          ]
        }
      ],
      "answered": 0
    },
    {
      "words": [
        {
          "word": "water",
          "transcription": "'wɔːtə",
          "partOfSpeech": "noun",
          "translations": [
            [
              "पानी"
            ]
          ]
        }
      ],
      "answered": 0
    },
    {
      "words": [
        {
          "word": "cold",
          "transcription": "kəuld",
          "partOfSpeech": "adjective",
          "translations": [
            [
              "ठंडा"
            ]
          ]
        }
      ],
      "answered": 0
    },
    {
      "words": [
        {
          "word": "cyclone",
          "transcription": "'saikləun",
          "partOfSpeech": "noun",
          "translations": [
            [
              "चक्रवात"
            ]
          ]
        }
      ],
      "answered": 0
    },
    {
      "words": [
        {
          "word": "storm",
          "transcription": "stɔːm",
          "partOfSpeech": "noun",
          "translations": [
            [
              "तूफान"
            ]
          ]
        }
      ],
      "answered": 0
    },
    {
      "words": [
        {
          "word": "clear",
          "transcription": "kliə",
          "partOfSpeech": "adjective",
          "translations": [
            [
              "साफ़"
            ]
          ]
        }
      ],
      "answered": 0
    },
    {
      "words": [
        {
          "word": "sleet",
          "transcription": "sliːt",
          "partOfSpeech": "noun",
          "translations": [
            [
              "ओलावृष्टि"
            ]
          ]
        }
      ],
      "answered": 0
    },
    {
      "words": [
        {
          "word": "cloud",
          "transcription": "klaud",
          "partOfSpeech": "noun",
          "translations": [
            [
              "बादल"
            ]
          ]
        }
      ],
      "answered": 0
    },
    {
      "words": [
        {
          "word": "chilly",
          "transcription": "'ʧili",
          "partOfSpeech": "adjective",
          "translations": [
            [
              "ठंडा"
            ]
          ]
        }
      ],
      "answered": 0
    },
    {
      "words": [
        {
          "word": "downpour",
          "transcription": "'daunpɔː",
          "partOfSpeech": "noun",
          "translations": [
            [
              "मूसलाधार बारिश"
            ]
          ]
        }
      ],
      "answered": 0
    },
    {
      "words": [
        {
          "word": "gale",
          "transcription": "geil",
          "partOfSpeech": "noun",
          "translations": [
            [
              "तेज हवा"
            ]
          ]
        }
      ],
      "answered": 0
    },
    {
      "words": [
        {
          "word": "scorching",
          "transcription": "'skɔːʧiŋ",
          "partOfSpeech": "adjective",
          "translations": [
            [
              "झुलसाने वाला"
            ]
          ]
        }
      ],
      "answered": 0
    },
    {
      "words": [
        {
          "word": "dust",
          "transcription": "dʌst",
          "partOfSpeech": "noun",
          "translations": [
            [
              "धूल"
            ]
          ]
        }
      ],
      "answered": 0
    },
    {
      "words": [
        {
          "word": "blustery",
          "transcription": "'blʌstəri",
          "partOfSpeech": "adjective",
          "translations": [
            [
              "तेज़ हवा वाला"
            ]
          ]
        }
      ],
      "answered": 0
    },
    {
      "words": [
        {
          "word": "overcast",
          "transcription": "'əuvəkɑːst",
          "partOfSpeech": "adjective",
          "translations": [
            [
              "घने बादल"
            ]
          ]
        }
      ],
      "answered": 0
    }
  ]
}